heaserver/fileawss3/__init__.py
heaserver/fileawss3/action.py
heaserver/fileawss3/context.py
heaserver/fileawss3/service.py
heaserver/fileawss3/wstl/all.json
heaserver_files_aws_s3-1.2.2.dist-info/LICENSE
heaserver_files_aws_s3-1.2.2.dist-info/METADATA
heaserver_files_aws_s3-1.2.2.dist-info/WHEEL
heaserver_files_aws_s3-1.2.2.dist-info/entry_points.txt
heaserver_files_aws_s3-1.2.2.dist-info/top_level.txt
heaserver_files_aws_s3-1.2.2.dist-info/RECORD
